rtl/axi_lite_slave.v
module axi_lite_slave #(
    parameter DATA_WIDTH = 32,
    parameter ADDR_WIDTH = 32,
    parameter NUM_REGS   = 4
)(
    input  wire                  clk,
    input  wire                  rst,

    // Write address channel
    input  wire                  awvalid,
    input  wire [ADDR_WIDTH-1:0] awaddr,
    output reg                   awready,

    // Write data channel
    input  wire                  wvalid,
    input  wire [DATA_WIDTH-1:0] wdata,
    input  wire [DATA_WIDTH/8-1:0] wstrb,
    output reg                   wready,

    // Write response channel
    output reg                   bvalid,
    output reg  [1:0]            bresp,
    input  wire                  bready,

    // Read address channel
    input  wire                  arvalid,
    input  wire [ADDR_WIDTH-1:0] araddr,
    output reg                   arready,

    // Read data channel
    output reg                   rvalid,
    output reg  [DATA_WIDTH-1:0] rdata,
    output reg  [1:0]            rresp,
    input  wire                  rready
);

    // Register file: 4 x 32-bit registers
    reg [DATA_WIDTH-1:0] regfile [0:NUM_REGS-1];

    // Internal address latches
    reg [ADDR_WIDTH-1:0] aw_addr_lat;
    reg                  aw_active;

    integer i;

    always @(posedge clk) begin
        if (rst) begin
            awready   <= 0;
            wready    <= 0;
            bvalid    <= 0;
            bresp     <= 2'b00;
            arready   <= 0;
            rvalid    <= 0;
            rdata     <= 0;
            rresp     <= 2'b00;
            aw_active <= 0;
            aw_addr_lat <= 0;
            for (i = 0; i < NUM_REGS; i = i + 1)
                regfile[i] <= 0;
        end else begin

            // ---- WRITE ADDRESS CHANNEL ----
            if (awvalid && !awready && !aw_active) begin
                awready     <= 1;
                aw_addr_lat <= awaddr;
                aw_active   <= 1;
            end else begin
                awready <= 0;
            end

            // ---- WRITE DATA CHANNEL ----
            if (wvalid && !wready && aw_active) begin
                wready <= 1;
                // WSTRB: only write bytes where strobe is high
                if (wstrb[0]) regfile[aw_addr_lat[3:2]][7:0]   <= wdata[7:0];
                if (wstrb[1]) regfile[aw_addr_lat[3:2]][15:8]  <= wdata[15:8];
                if (wstrb[2]) regfile[aw_addr_lat[3:2]][23:16] <= wdata[23:16];
                if (wstrb[3]) regfile[aw_addr_lat[3:2]][31:24] <= wdata[31:24];
                bvalid    <= 1;
                bresp     <= 2'b00; // OKAY
                aw_active <= 0;
            end else begin
                wready <= 0;
            end

            // ---- WRITE RESPONSE CHANNEL ----
            if (bvalid && bready) begin
                bvalid <= 0;
            end

            // ---- READ ADDRESS CHANNEL ----
            if (arvalid && !arready && !rvalid) begin
                arready <= 1;
                rdata   <= regfile[araddr[3:2]];
                rresp   <= 2'b00; // OKAY
                rvalid  <= 1;
            end else begin
                arready <= 0;
            end

            // ---- READ DATA CHANNEL ----
            if (rvalid && rready) begin
                rvalid <= 0;
            end

        end
    end

endmodule

tb/tb_axi_lite.v
`timescale 1ns/1ps

module tb_axi_lite;

    // -------------------------------------------------------
    // Parameters
    // -------------------------------------------------------
    parameter DATA_WIDTH = 32;
    parameter ADDR_WIDTH = 32;
    parameter NUM_REGS   = 4;

    // -------------------------------------------------------
    // Clock & Reset
    // -------------------------------------------------------
    reg clk = 0;
    reg rst = 1;
    always #5 clk = ~clk; // 100MHz

    // -------------------------------------------------------
    // DUT Signals
    // -------------------------------------------------------
    reg                    awvalid;
    reg  [ADDR_WIDTH-1:0]  awaddr;
    wire                   awready;

    reg                    wvalid;
    reg  [DATA_WIDTH-1:0]  wdata;
    reg  [3:0]             wstrb;
    wire                   wready;

    wire                   bvalid;
    wire [1:0]             bresp;
    reg                    bready;

    reg                    arvalid;
    reg  [ADDR_WIDTH-1:0]  araddr;
    wire                   arready;

    wire                   rvalid;
    wire [DATA_WIDTH-1:0]  rdata;
    wire [1:0]             rresp;
    reg                    rready;

    // -------------------------------------------------------
    // DUT Instantiation
    // -------------------------------------------------------
    axi_lite_slave #(
        .DATA_WIDTH(DATA_WIDTH),
        .ADDR_WIDTH(ADDR_WIDTH),
        .NUM_REGS(NUM_REGS)
    ) dut (
        .clk(clk), .rst(rst),
        .awvalid(awvalid), .awaddr(awaddr), .awready(awready),
        .wvalid(wvalid),   .wdata(wdata),   .wstrb(wstrb),   .wready(wready),
        .bvalid(bvalid),   .bresp(bresp),   .bready(bready),
        .arvalid(arvalid), .araddr(araddr), .arready(arready),
        .rvalid(rvalid),   .rdata(rdata),   .rresp(rresp),   .rready(rready)
    );

    // -------------------------------------------------------
    // Scoreboard: track expected register values
    // -------------------------------------------------------
    reg [DATA_WIDTH-1:0] expected_regs [0:NUM_REGS-1];
    integer pass_count = 0;
    integer fail_count = 0;

    // -------------------------------------------------------
    // Assertions
    // -------------------------------------------------------

    // Previous cycle signals for edge detection
    reg awvalid_prev, wvalid_prev, arvalid_prev;
    reg awready_prev, wready_prev, arready_prev;
    always @(posedge clk) begin
        awvalid_prev <= awvalid;
        wvalid_prev  <= wvalid;
        arvalid_prev <= arvalid;
        awready_prev <= awready;
        wready_prev  <= wready;
        arready_prev <= arready;
    end

    // VALID must not deassert once raised until handshake occurs
    always @(posedge clk) begin
        if (!rst) begin
            // AWVALID stability
            if (awvalid_prev && !awvalid && !awready && !awready_prev)
                $display("ASSERTION FAIL [%0t]: awvalid deasserted without handshake", $time);

            // WVALID stability
            if (wvalid_prev && !wvalid && !wready && !wready_prev)
                $display("ASSERTION FAIL [%0t]: wvalid deasserted without handshake", $time);

            // ARVALID stability
            if (arvalid_prev && !arvalid && !arready && !arready_prev)
                $display("ASSERTION FAIL [%0t]: arvalid deasserted without handshake", $time);

            // BRESP must be OKAY on valid response
            if (bvalid && bresp !== 2'b00)
                $display("ASSERTION FAIL [%0t]: unexpected bresp = %b", $time, bresp);

            // RRESP must be OKAY on valid read
            if (rvalid && rresp !== 2'b00)
                $display("ASSERTION FAIL [%0t]: unexpected rresp = %b", $time, rresp);
        end
    end

    // -------------------------------------------------------
    // Coverage
    // -------------------------------------------------------
    reg cov_write_reg0 = 0;
    reg cov_write_reg1 = 0;
    reg cov_write_reg2 = 0;
    reg cov_write_reg3 = 0;
    reg cov_read_reg0  = 0;
    reg cov_read_reg1  = 0;
    reg cov_read_reg2  = 0;
    reg cov_read_reg3  = 0;
    reg cov_wstrb_byte = 0; // partial byte write
    reg cov_back2back  = 0; // back-to-back transactions

    task update_write_coverage;
        input [ADDR_WIDTH-1:0] addr;
        input [3:0]            strb;
        begin
            case (addr[3:2])
                2'd0: cov_write_reg0 = 1;
                2'd1: cov_write_reg1 = 1;
                2'd2: cov_write_reg2 = 1;
                2'd3: cov_write_reg3 = 1;
            endcase
            if (strb !== 4'hF) cov_wstrb_byte = 1;
        end
    endtask

    task update_read_coverage;
        input [ADDR_WIDTH-1:0] addr;
        begin
            case (addr[3:2])
                2'd0: cov_read_reg0 = 1;
                2'd1: cov_read_reg1 = 1;
                2'd2: cov_read_reg2 = 1;
                2'd3: cov_read_reg3 = 1;
            endcase
        end
    endtask

    task print_coverage;
        integer hits, total;
        begin
            hits  = cov_write_reg0 + cov_write_reg1 + cov_write_reg2 + cov_write_reg3 +
                    cov_read_reg0  + cov_read_reg1  + cov_read_reg2  + cov_read_reg3  +
                    cov_wstrb_byte + cov_back2back;
            total = 10;
            $display("--------------------------------------------------");
            $display("FUNCTIONAL COVERAGE REPORT");
            $display("  Write reg0       : %s", cov_write_reg0 ? "HIT" : "MISS");
            $display("  Write reg1       : %s", cov_write_reg1 ? "HIT" : "MISS");
            $display("  Write reg2       : %s", cov_write_reg2 ? "HIT" : "MISS");
            $display("  Write reg3       : %s", cov_write_reg3 ? "HIT" : "MISS");
            $display("  Read  reg0       : %s", cov_read_reg0  ? "HIT" : "MISS");
            $display("  Read  reg1       : %s", cov_read_reg1  ? "HIT" : "MISS");
            $display("  Read  reg2       : %s", cov_read_reg2  ? "HIT" : "MISS");
            $display("  Read  reg3       : %s", cov_read_reg3  ? "HIT" : "MISS");
            $display("  Partial WSTRB    : %s", cov_wstrb_byte ? "HIT" : "MISS");
            $display("  Back-to-back     : %s", cov_back2back  ? "HIT" : "MISS");
            $display("  Coverage         : %0d / %0d (%0d%%)", hits, total, (hits*100)/total);
            $display("--------------------------------------------------");
        end
    endtask

    // -------------------------------------------------------
    // Tasks: Write & Read
    // -------------------------------------------------------
    task axi_write;
        input [ADDR_WIDTH-1:0] addr;
        input [DATA_WIDTH-1:0] data;
        input [3:0]            strb;
        integer byte_idx;
        reg [DATA_WIDTH-1:0] masked;
        begin
            // Drive AW channel
            awaddr  = addr;
            awvalid = 1;
            @(posedge clk);
            while (!awready) @(posedge clk);
            awvalid = 0;
            @(posedge clk);

            // Drive W channel
            wdata  = data;
            wstrb  = strb;
            wvalid = 1;
            bready = 1;
            @(posedge clk);
            while (!wready) @(posedge clk);
            wvalid = 0;

            // Wait for write response
            while (!bvalid) @(posedge clk);
            @(posedge clk);
            bready = 0;

            // Update scoreboard
            masked = expected_regs[addr[3:2]];
            for (byte_idx = 0; byte_idx < 4; byte_idx = byte_idx + 1) begin
                if (strb[byte_idx])
                    masked[byte_idx*8 +: 8] = data[byte_idx*8 +: 8];
            end
            expected_regs[addr[3:2]] = masked;

            update_write_coverage(addr, strb);
        end
    endtask

    task axi_read;
        input  [ADDR_WIDTH-1:0] addr;
        output [DATA_WIDTH-1:0] data_out;
        begin
            araddr  = addr;
            arvalid = 1;
            rready  = 1;

            @(posedge clk);
            while (!arready) @(posedge clk);
            arvalid = 0;

            while (!rvalid) @(posedge clk);
            data_out = rdata;
            @(posedge clk);
            rready = 0;

            update_read_coverage(addr);
        end
    endtask

    // -------------------------------------------------------
    // Stimulus: Constrained-Random + Directed Tests
    // -------------------------------------------------------
    integer seed = 42;
    integer t;
    reg [DATA_WIDTH-1:0] rand_data;
    reg [1:0]            rand_reg;
    reg [3:0]            rand_strb;
    reg [DATA_WIDTH-1:0] read_result;

    initial begin
        $dumpfile("waveforms/axi.vcd");
        $dumpvars(0, tb_axi_lite);

        // Init signals
        awvalid = 0; awaddr = 0;
        wvalid  = 0; wdata  = 0; wstrb = 4'hF;
        bready  = 0;
        arvalid = 0; araddr = 0;
        rready  = 0;

        // Init scoreboard
        for (t = 0; t < NUM_REGS; t = t + 1)
            expected_regs[t] = 0;

        // Release reset
        repeat(3) @(posedge clk);
        rst = 0;
        repeat(2) @(posedge clk);

        $display("=== TEST 1: Directed Full-Word Writes to All Registers ===");
        axi_write(32'h00, 32'hDEADBEEF, 4'hF);
        axi_write(32'h04, 32'hCAFEBABE, 4'hF);
        axi_write(32'h08, 32'hA5A5A5A5, 4'hF);
        axi_write(32'h0C, 32'h12345678, 4'hF);

        $display("=== TEST 2: Directed Reads & Scoreboard Check ===");
        axi_read(32'h00, read_result);
        if (read_result === expected_regs[0])
            begin $display("PASS reg0: got %h", read_result); pass_count = pass_count + 1; end
        else
            begin $display("FAIL reg0: got %h, exp %h", read_result, expected_regs[0]); fail_count = fail_count + 1; end

        axi_read(32'h04, read_result);
        if (read_result === expected_regs[1])
            begin $display("PASS reg1: got %h", read_result); pass_count = pass_count + 1; end
        else
            begin $display("FAIL reg1: got %h, exp %h", read_result, expected_regs[1]); fail_count = fail_count + 1; end

        axi_read(32'h08, read_result);
        if (read_result === expected_regs[2])
            begin $display("PASS reg2: got %h", read_result); pass_count = pass_count + 1; end
        else
            begin $display("FAIL reg2: got %h, exp %h", read_result, expected_regs[2]); fail_count = fail_count + 1; end

        axi_read(32'h0C, read_result);
        if (read_result === expected_regs[3])
            begin $display("PASS reg3: got %h", read_result); pass_count = pass_count + 1; end
        else
            begin $display("FAIL reg3: got %h, exp %h", read_result, expected_regs[3]); fail_count = fail_count + 1; end

        $display("=== TEST 3: Partial WSTRB Write (lower 2 bytes only) ===");
        axi_write(32'h00, 32'hFFFFFFFF, 4'b0011);
        axi_read(32'h00, read_result);
        if (read_result === expected_regs[0])
            begin $display("PASS WSTRB: got %h", read_result); pass_count = pass_count + 1; end
        else
            begin $display("FAIL WSTRB: got %h, exp %h", read_result, expected_regs[0]); fail_count = fail_count + 1; end

        $display("=== TEST 4: Constrained-Random Writes & Readback ===");
        repeat(8) begin
            rand_data = $random(seed);
            rand_reg  = $random(seed) % NUM_REGS;
            rand_strb = 4'hF; // full word for random tests
            axi_write({30'b0, rand_reg, 2'b00}, rand_data, rand_strb);
            axi_read ({30'b0, rand_reg, 2'b00}, read_result);
            if (read_result === expected_regs[rand_reg])
                begin $display("PASS rand reg%0d: got %h", rand_reg, read_result); pass_count = pass_count + 1; end
            else
                begin $display("FAIL rand reg%0d: got %h, exp %h", rand_reg, read_result, expected_regs[rand_reg]); fail_count = fail_count + 1; end
        end

        $display("=== TEST 5: Back-to-Back Transactions ===");
        cov_back2back = 1;
        axi_write(32'h00, 32'hAABBCCDD, 4'hF);
        axi_write(32'h04, 32'h11223344, 4'hF);
        axi_read(32'h00, read_result);
        if (read_result === expected_regs[0])
            begin $display("PASS back2back reg0: got %h", read_result); pass_count = pass_count + 1; end
        else
            begin $display("FAIL back2back reg0: got %h, exp %h", read_result, expected_regs[0]); fail_count = fail_count + 1; end

        // -------------------------------------------------------
        // Final Report
        // -------------------------------------------------------
        repeat(2) @(posedge clk);
        $display("==================================================");
        $display("TEST SUMMARY: %0d PASSED | %0d FAILED", pass_count, fail_count);
        $display("==================================================");
        print_coverage();

        $finish;
    end

endmodule

waveforms/axi.vcd
$date
	Tue Mar 17 19:43:08 2026
$end
$version
	Icarus Verilog
$end
$timescale
	1ps
$end
$scope module tb_axi_lite $end
$var wire 1 ! wready $end
$var wire 1 " rvalid $end
$var wire 2 # rresp [1:0] $end
$var wire 32 $ rdata [31:0] $end
$var wire 1 % bvalid $end
$var wire 2 & bresp [1:0] $end
$var wire 1 ' awready $end
$var wire 1 ( arready $end
$var parameter 32 ) ADDR_WIDTH $end
$var parameter 32 * DATA_WIDTH $end
$var parameter 32 + NUM_REGS $end
$var reg 32 , araddr [31:0] $end
$var reg 1 - arready_prev $end
$var reg 1 . arvalid $end
$var reg 1 / arvalid_prev $end
$var reg 32 0 awaddr [31:0] $end
$var reg 1 1 awready_prev $end
$var reg 1 2 awvalid $end
$var reg 1 3 awvalid_prev $end
$var reg 1 4 bready $end
$var reg 1 5 clk $end
$var reg 1 6 cov_back2back $end
$var reg 1 7 cov_read_reg0 $end
$var reg 1 8 cov_read_reg1 $end
$var reg 1 9 cov_read_reg2 $end
$var reg 1 : cov_read_reg3 $end
$var reg 1 ; cov_write_reg0 $end
$var reg 1 < cov_write_reg1 $end
$var reg 1 = cov_write_reg2 $end
$var reg 1 > cov_write_reg3 $end
$var reg 1 ? cov_wstrb_byte $end
$var reg 32 @ rand_data [31:0] $end
$var reg 2 A rand_reg [1:0] $end
$var reg 4 B rand_strb [3:0] $end
$var reg 32 C read_result [31:0] $end
$var reg 1 D rready $end
$var reg 1 E rst $end
$var reg 32 F wdata [31:0] $end
$var reg 1 G wready_prev $end
$var reg 4 H wstrb [3:0] $end
$var reg 1 I wvalid $end
$var reg 1 J wvalid_prev $end
$var integer 32 K fail_count [31:0] $end
$var integer 32 L pass_count [31:0] $end
$var integer 32 M seed [31:0] $end
$var integer 32 N t [31:0] $end
$scope module dut $end
$var wire 32 O araddr [31:0] $end
$var wire 1 . arvalid $end
$var wire 32 P awaddr [31:0] $end
$var wire 1 2 awvalid $end
$var wire 1 4 bready $end
$var wire 1 5 clk $end
$var wire 1 D rready $end
$var wire 1 E rst $end
$var wire 32 Q wdata [31:0] $end
$var wire 4 R wstrb [3:0] $end
$var wire 1 I wvalid $end
$var parameter 32 S ADDR_WIDTH $end
$var parameter 32 T DATA_WIDTH $end
$var parameter 32 U NUM_REGS $end
$var reg 1 ( arready $end
$var reg 1 V aw_active $end
$var reg 32 W aw_addr_lat [31:0] $end
$var reg 1 ' awready $end
$var reg 2 X bresp [1:0] $end
$var reg 1 % bvalid $end
$var reg 32 Y rdata [31:0] $end
$var reg 2 Z rresp [1:0] $end
$var reg 1 " rvalid $end
$var reg 1 ! wready $end
$var integer 32 [ i [31:0] $end
$upscope $end
$scope task axi_read $end
$var reg 32 \ addr [31:0] $end
$var reg 32 ] data_out [31:0] $end
$upscope $end
$scope task axi_write $end
$var reg 32 ^ addr [31:0] $end
$var reg 32 _ data [31:0] $end
$var reg 32 ` masked [31:0] $end
$var reg 4 a strb [3:0] $end
$var integer 32 b byte_idx [31:0] $end
$upscope $end
$scope task print_coverage $end
$var integer 32 c hits [31:0] $end
$var integer 32 d total [31:0] $end
$upscope $end
$scope task update_read_coverage $end
$var reg 32 e addr [31:0] $end
$upscope $end
$scope task update_write_coverage $end
$var reg 32 f addr [31:0] $end
$var reg 4 g strb [3:0] $end
$upscope $end
$upscope $end
$enddefinitions $end
$comment Show the parameter values. $end
$dumpall
b100 U
b100000 T
b100000 S
b100 +
b100000 *
b100000 )
$end
#0
$dumpvars
bx g
bx f
bx e
bx d
bx c
bx b
bx a
bx `
bx _
bx ^
bx ]
bx \
bx [
bx Z
bx Y
bx X
bx W
xV
b1111 R
b0 Q
b0 P
b0 O
b100 N
b101010 M
b0 L
b0 K
xJ
0I
b1111 H
xG
b0 F
1E
0D
bx C
bx B
bx A
bx @
0?
0>
0=
0<
0;
0:
09
08
07
06
05
04
x3
02
x1
b0 0
x/
0.
x-
b0 ,
x(
x'
bx &
x%
bx $
bx #
x"
x!
$end
#5000
b0 W
0V
b0 #
b0 Z
b0 $
b0 Y
0"
0(
b0 &
b0 X
0%
0!
0'
0/
0J
03
b100 [
15
#10000
05
#15000
0-
0G
01
b100 [
15
#20000
05
#25000
0E
15
#30000
05
#35000
15
#40000
05
#45000
12
b1111 a
b11011110101011011011111011101111 _
b0 ^
15
#50000
05
#55000
13
1V
1'
15
#60000
05
#65000
0'
11
02
15
#70000
05
#75000
01
1J
03
0V
1%
1!
14
1I
b11011110101011011011111011101111 F
b11011110101011011011111011101111 Q
15
#80000
05
#85000
0%
0!
1G
0I
15
#90000
05
#95000
0G
0J
12
b100 0
b100 P
b11001010111111101011101010111110 _
b100 ^
1;
b1111 g
b0 f
b100 b
b11011110101011011011111011101111 `
04
15
#100000
05
#105000
1V
b100 W
1'
13
15
#110000
05
#115000
11
0'
02
15
#120000
05
#125000
0V
1%
1!
01
1J
03
14
1I
b11001010111111101011101010111110 F
b11001010111111101011101010111110 Q
15
#130000
05
#135000
1G
0%
0!
0I
15
#140000
05
#145000
0G
0J
12
b1000 0
b1000 P
b10100101101001011010010110100101 _
b1000 ^
1<
b100 f
b100 b
b11001010111111101011101010111110 `
04
15
#150000
05
#155000
13
1V
b1000 W
1'
15
#160000
05
#165000
0'
11
02
15
#170000
05
#175000
01
1J
03
0V
1%
1!
14
1I
b10100101101001011010010110100101 F
b10100101101001011010010110100101 Q
15
#180000
05
#185000
0%
0!
1G
0I
15
#190000
05
#195000
0G
0J
12
b1100 0
b1100 P
b10010001101000101011001111000 _
b1100 ^
1=
b1000 f
b100 b
b10100101101001011010010110100101 `
04
15
#200000
05
#205000
1V
b1100 W
1'
13
15
#210000
05
#215000
11
0'
02
15
#220000
05
#225000
0V
1%
1!
01
1J
03
14
1I
b10010001101000101011001111000 F
b10010001101000101011001111000 Q
15
#230000
05
#235000
1G
0%
0!
0I
15
#240000
05
#245000
0G
0J
1D
1.
b0 \
1>
b1100 f
b100 b
b10010001101000101011001111000 `
04
15
#250000
05
#255000
1/
1"
b11011110101011011011111011101111 $
b11011110101011011011111011101111 Y
1(
15
#260000
05
#265000
0"
0(
1-
b11011110101011011011111011101111 ]
0.
15
#270000
05
#275000
0-
0/
1.
b100 ,
b100 O
b100 \
b1 L
b11011110101011011011111011101111 C
17
b0 e
1D
15
#280000
05
#285000
1"
b11001010111111101011101010111110 $
b11001010111111101011101010111110 Y
1(
1/
15
#290000
05
#295000
1-
0"
0(
b11001010111111101011101010111110 ]
0.
15
#300000
05
#305000
0-
0/
1.
b1000 ,
b1000 O
b1000 \
b10 L
b11001010111111101011101010111110 C
18
b100 e
1D
15
#310000
05
#315000
1/
1"
b10100101101001011010010110100101 $
b10100101101001011010010110100101 Y
1(
15
#320000
05
#325000
0"
0(
1-
b10100101101001011010010110100101 ]
0.
15
#330000
05
#335000
0-
0/
1.
b1100 ,
b1100 O
b1100 \
b11 L
b10100101101001011010010110100101 C
19
b1000 e
1D
15
#340000
05
#345000
1"
b10010001101000101011001111000 $
b10010001101000101011001111000 Y
1(
1/
15
#350000
05
#355000
1-
0"
0(
b10010001101000101011001111000 ]
0.
15
#360000
05
#365000
0-
0/
12
b0 0
b0 P
b11 a
b11111111111111111111111111111111 _
b0 ^
b100 L
b10010001101000101011001111000 C
1:
b1100 e
0D
15
#370000
05
#375000
13
1V
b0 W
1'
15
#380000
05
#385000
0'
11
02
15
#390000
05
#395000
01
1J
03
0V
1%
1!
14
1I
b11 H
b11 R
b11111111111111111111111111111111 F
b11111111111111111111111111111111 Q
15
#400000
05
#405000
0%
0!
1G
0I
15
#410000
05
#415000
0G
0J
1D
1.
b0 ,
b0 O
b0 \
1?
b11 g
b0 f
b100 b
b11011110101011011111111111111111 `
04
15
#420000
05
#425000
1"
b11011110101011011111111111111111 $
b11011110101011011111111111111111 Y
1(
1/
15
#430000
05
#435000
1-
0"
0(
b11011110101011011111111111111111 ]
0.
15
#440000
05
#445000
0-
0/
12
b100 0
b100 P
b1111 a
b10000000001011000100010000000000 _
b100 ^
b1111 B
b1 A
b10000000001011000100010000000000 @
b10100110100001000111000010001000 M
b101 L
b11011110101011011111111111111111 C
b0 e
0D
15
#450000
05
#455000
13
1V
b100 W
1'
15
#460000
05
#465000
0'
11
02
15
#470000
05
#475000
01
1J
03
0V
1%
1!
14
1I
b1111 H
b1111 R
b10000000001011000100010000000000 F
b10000000001011000100010000000000 Q
15
#480000
05
#485000
0%
0!
1G
0I
15
#490000
05
#495000
0G
0J
1D
1.
b100 ,
b100 O
b100 \
b1111 g
b100 f
b100 b
b10000000001011000100010000000000 `
04
15
#500000
05
#505000
1"
b10000000001011000100010000000000 $
b10000000001011000100010000000000 Y
1(
1/
15
#510000
05
#515000
1-
0"
0(
b10000000001011000100010000000000 ]
0.
15
#520000
05
#525000
0-
0/
12
b1100 0
b1100 P
b10010011010000011100000100 _
b1100 ^
b11 A
b10010011010000011100000100 @
b1000101110101011100001110010110 M
b110 L
b10000000001011000100010000000000 C
b100 e
0D
15
#530000
05
#535000
13
1V
b1100 W
1'
15
#540000
05
#545000
0'
11
02
15
#550000
05
#555000
01
1J
03
0V
1%
1!
14
1I
b10010011010000011100000100 F
b10010011010000011100000100 Q
15
#560000
05
#565000
0%
0!
1G
0I
15
#570000
05
#575000
0G
0J
1D
1.
b1100 ,
b1100 O
b1100 \
b1100 f
b100 b
b10010011010000011100000100 `
04
15
#580000
05
#585000
1"
b10010011010000011100000100 $
b10010011010000011100000100 Y
1(
1/
15
#590000
05
#595000
1-
0"
0(
b10010011010000011100000100 ]
0.
15
#600000
05
#605000
0-
0/
12
b100 0
b100 P
b1010101100100011111100010101 _
b100 ^
b1 A
b1010101100100011111100010101 @
b1011010111101001000010011010100 M
b111 L
b10010011010000011100000100 C
b1100 e
0D
15
#610000
05
#615000
13
1V
b100 W
1'
15
#620000
05
#625000
0'
11
02
15
#630000
05
#635000
01
1J
03
0V
1%
1!
14
1I
b1010101100100011111100010101 F
b1010101100100011111100010101 Q
15
#640000
05
#645000
0%
0!
1G
0I
15
#650000
05
#655000
0G
0J
1D
1.
b100 ,
b100 O
b100 \
b100 f
b100 b
b1010101100100011111100010101 `
04
15
#660000
05
#665000
1"
b1010101100100011111100010101 $
b1010101100100011111100010101 Y
1(
1/
15
#670000
05
#675000
1-
0"
0(
b1010101100100011111100010101 ]
0.
15
#680000
05
#685000
0-
0/
12
b1000 0
b1000 P
b1000101011000010010001110001010 _
b1000 ^
b10 A
b1000101011000010010001110001010 @
b11111010001000000101111000010 M
b1000 L
b1010101100100011111100010101 C
b100 e
0D
15
#690000
05
#695000
13
1V
b1000 W
1'
15
#700000
05
#705000
0'
11
02
15
#710000
05
#715000
01
1J
03
0V
1%
1!
14
1I
b1000101011000010010001110001010 F
b1000101011000010010001110001010 Q
15
#720000
05
#725000
0%
0!
1G
0I
15
#730000
05
#735000
0G
0J
1D
1.
b1000 ,
b1000 O
b1000 \
b1000 f
b100 b
b1000101011000010010001110001010 `
04
15
#740000
05
#745000
1"
b1000101011000010010001110001010 $
b1000101011000010010001110001010 Y
1(
1/
15
#750000
05
#755000
1-
0"
0(
b1000101011000010010001110001010 ]
0.
15
#760000
05
#765000
0-
0/
12
b0 0
b0 P
b1001110110000100011100010011 _
b0 ^
b0 A
b1001110110000100011100010011 @
b10100010000000100101101111100000 M
b1001 L
b1000101011000010010001110001010 C
b1000 e
0D
15
#770000
05
#775000
13
1V
b0 W
1'
15
#780000
05
#785000
0'
11
02
15
#790000
05
#795000
01
1J
03
0V
1%
1!
14
1I
b1001110110000100011100010011 F
b1001110110000100011100010011 Q
15
#800000
05
#805000
0%
0!
1G
0I
15
#810000
05
#815000
0G
0J
1D
1.
b0 ,
b0 O
b0 \
b0 f
b100 b
b1001110110000100011100010011 `
04
15
#820000
05
#825000
1"
b1001110110000100011100010011 $
b1001110110000100011100010011 Y
1(
1/
15
#830000
05
#835000
1-
0"
0(
b1001110110000100011100010011 ]
0.
15
#840000
05
#845000
0-
0/
12
b1100 0
b1100 P
b10110110011011011111010001101100 _
b1100 ^
b11 A
b10110110011011011111010001101100 @
b11101101110110000010010101110 M
b1010 L
b1001110110000100011100010011 C
b0 e
0D
15
#850000
05
#855000
13
1V
b1100 W
1'
15
#860000
05
#865000
0'
11
02
15
#870000
05
#875000
01
1J
03
0V
1%
1!
14
1I
b10110110011011011111010001101100 F
b10110110011011011111010001101100 Q
15
#880000
05
#885000
0%
0!
1G
0I
15
#890000
05
#895000
0G
0J
1D
1.
b1100 ,
b1100 O
b1100 \
b1100 f
b100 b
b10110110011011011111010001101100 `
04
15
#900000
05
#905000
1"
b10110110011011011111010001101100 $
b10110110011011011111010001101100 Y
1(
1/
15
#910000
05
#915000
1-
0"
0(
b10110110011011011111010001101100 ]
0.
15
#920000
05
#925000
0-
0/
12
b100 0
b100 P
b11010010101011011001011010100101 _
b100 ^
b1 A
b11010010101011011001011010100101 @
b10011010111011010000000110101100 M
b1011 L
b10110110011011011111010001101100 C
b1100 e
0D
15
#930000
05
#935000
13
1V
b100 W
1'
15
#940000
05
#945000
0'
11
02
15
#950000
05
#955000
01
1J
03
0V
1%
1!
14
1I
b11010010101011011001011010100101 F
b11010010101011011001011010100101 Q
15
#960000
05
#965000
0%
0!
1G
0I
15
#970000
05
#975000
0G
0J
1D
1.
b100 ,
b100 O
b100 \
b100 f
b100 b
b11010010101011011001011010100101 `
04
15
#980000
05
#985000
1"
b11010010101011011001011010100101 $
b11010010101011011001011010100101 Y
1(
1/
15
#990000
05
#995000
1-
0"
0(
b11010010101011011001011010100101 ]
0.
15
#1000000
05
#1005000
0-
0/
12
b1100 0
b1100 P
b10011010100011000001010000110101 _
b1100 ^
b11 A
b10011010100011000001010000110101 @
b1110001110110111001101001011010 M
b1100 L
b11010010101011011001011010100101 C
b100 e
0D
15
#1010000
05
#1015000
13
1V
b1100 W
1'
15
#1020000
05
#1025000
0'
11
02
15
#1030000
05
#1035000
01
1J
03
0V
1%
1!
14
1I
b10011010100011000001010000110101 F
b10011010100011000001010000110101 Q
15
#1040000
05
#1045000
0%
0!
1G
0I
15
#1050000
05
#1055000
0G
0J
1D
1.
b1100 ,
b1100 O
b1100 \
b1100 f
b100 b
b10011010100011000001010000110101 `
04
15
#1060000
05
#1065000
1"
b10011010100011000001010000110101 $
b10011010100011000001010000110101 Y
1(
1/
15
#1070000
05
#1075000
1-
0"
0(
b10011010100011000001010000110101 ]
0.
15
#1080000
05
#1085000
0-
0/
12
b0 0
b0 P
b10101010101110111100110011011101 _
b0 ^
16
b1101 L
b10011010100011000001010000110101 C
b1100 e
0D
15
#1090000
05
#1095000
13
1V
b0 W
1'
15
#1100000
05
#1105000
0'
11
02
15
#1110000
05
#1115000
01
1J
03
0V
1%
1!
14
1I
b10101010101110111100110011011101 F
b10101010101110111100110011011101 Q
15
#1120000
05
#1125000
0%
0!
1G
0I
15
#1130000
05
#1135000
0G
0J
12
b100 0
b100 P
b10001001000100011001101000100 _
b100 ^
b0 f
b100 b
b10101010101110111100110011011101 `
04
15
#1140000
05
#1145000
1V
b100 W
1'
13
15
#1150000
05
#1155000
11
0'
02
15
#1160000
05
#1165000
0V
1%
1!
01
1J
03
14
1I
b10001001000100011001101000100 F
b10001001000100011001101000100 Q
15
#1170000
05
#1175000
1G
0%
0!
0I
15
#1180000
05
#1185000
0G
0J
1D
1.
b0 ,
b0 O
b0 \
b100 f
b100 b
b10001001000100011001101000100 `
04
15
#1190000
05
#1195000
1/
1"
b10101010101110111100110011011101 $
b10101010101110111100110011011101 Y
1(
15
#1200000
05
#1205000
0"
0(
1-
b10101010101110111100110011011101 ]
0.
15
#1210000
05
#1215000
0-
0/
b1110 L
b10101010101110111100110011011101 C
b0 e
0D
15
#1220000
05
#1225000
15
#1230000
05
#1235000
b1010 d
b1010 c
15
